hetman_pipeline-2.2.4.dist-info/licenses/LICENSE
pipeline/__init__.py
pipeline/py.typed
pipeline/core/__init__.py
pipeline/core/pipe/__init__.py
pipeline/core/pipe/pipe.py
pipeline/core/pipe/resources/__init__.py
pipeline/core/pipe/resources/constants.py
pipeline/core/pipe/resources/types.py
pipeline/core/pipeline/__init__.py
pipeline/core/pipeline/pipeline.py
pipeline/core/pipeline/resources/__init__.py
pipeline/core/pipeline/resources/constants.py
pipeline/core/pipeline/resources/exceptions.py
pipeline/core/pipeline/resources/types.py
pipeline/handlers/__init__.py
pipeline/handlers/base_handler/__init__.py
pipeline/handlers/base_handler/base_handler.py
pipeline/handlers/base_handler/handler_modifiers.py
pipeline/handlers/base_handler/resources/__init__.py
pipeline/handlers/base_handler/resources/constants.py
pipeline/handlers/base_handler/resources/exceptions.py
pipeline/handlers/condition_handler/__init__.py
pipeline/handlers/condition_handler/condition.py
pipeline/handlers/condition_handler/condition_handler.py
pipeline/handlers/condition_handler/resources/__init__.py
pipeline/handlers/condition_handler/resources/constants.py
pipeline/handlers/condition_handler/resources/exceptions.py
pipeline/handlers/condition_handler/resources/types.py
pipeline/handlers/match_handler/__init__.py
pipeline/handlers/match_handler/match.py
pipeline/handlers/match_handler/match_handler.py
pipeline/handlers/match_handler/units/__init__.py
pipeline/handlers/match_handler/units/match_encoding.py
pipeline/handlers/match_handler/units/match_format.py
pipeline/handlers/match_handler/units/match_localization.py
pipeline/handlers/match_handler/units/match_network.py
pipeline/handlers/match_handler/units/match_regex.py
pipeline/handlers/match_handler/units/match_text.py
pipeline/handlers/match_handler/units/match_time.py
pipeline/handlers/match_handler/units/match_web.py
pipeline/handlers/match_handler/units/resources/__init__.py
pipeline/handlers/match_handler/units/resources/constants.py
pipeline/handlers/transform_handler/__init__.py
hetman_pipeline-2.2.4.dist-info/METADATA
hetman_pipeline-2.2.4.dist-info/WHEEL
hetman_pipeline-2.2.4.dist-info/top_level.txt
hetman_pipeline-2.2.4.dist-info/RECORD
